tuplevector/__init__.py
tuplevector/test_tuplevector.py
tuplevector-1.0.0.dist-info/LICENSE.TXT
tuplevector-1.0.0.dist-info/METADATA
tuplevector-1.0.0.dist-info/WHEEL
tuplevector-1.0.0.dist-info/top_level.txt
tuplevector-1.0.0.dist-info/RECORD
