Metadata-Version: 2.1
Name: tuplevector
Version: 1.0.0
Summary: Simple library for performing vector math on tuples and NamedTuples.
Home-page: https://github.com/connorferster/tuplevector
Author: Connor Ferster
Author-email: connorferster@gmail.com
License: MIT
Platform: UNKNOWN
Classifier: Topic :: Scientific/Engineering :: Mathematics
Classifier: Programming Language :: Python :: 3
Classifier: License :: OSI Approved :: MIT License
Classifier: Operating System :: OS Independent
Requires-Python: >=3.6.0
